{"nodes": [{"id": "users_yajan_desktop_evalgate_src_ankora_diff_py", "label": "diff.py", "file_type": "code", "source_file": "src/ankora/diff.py", "source_location": "L1"}, {"id": "users_yajan_desktop_evalgate_src_ankora_diff_casestatus", "label": "CaseStatus", "file_type": "code", "source_file": "src/ankora/diff.py", "source_location": "L25", "_callable": true}, {"id": "strenum", "label": "StrEnum", "file_type": "code", "source_file": "", "source_location": ""}, {"id": "users_yajan_desktop_evalgate_src_ankora_diff_casediff", "label": "CaseDiff", "file_type": "code", "source_file": "src/ankora/diff.py", "source_location": "L36", "_callable": true}, {"id": "basemodel", "label": "BaseModel", "file_type": "code", "source_file": "", "source_location": ""}, {"id": "users_yajan_desktop_evalgate_src_ankora_diff_diffreport", "label": "DiffReport", "file_type": "code", "source_file": "src/ankora/diff.py", "source_location": "L50", "_callable": true}, {"id": "users_yajan_desktop_evalgate_src_ankora_diff_diff_runs", "label": "diff_runs()", "file_type": "code", "source_file": "src/ankora/diff.py", "source_location": "L65", "_callable": true}, {"id": "runresult", "label": "RunResult", "file_type": "code", "source_file": "", "source_location": "", "origin_file": "/Users/yajan/Desktop/evalgate/src/ankora/diff.py"}, {"id": "config", "label": "Config", "file_type": "code", "source_file": "", "source_location": "", "origin_file": "/Users/yajan/Desktop/evalgate/src/ankora/diff.py"}, {"id": "users_yajan_desktop_evalgate_src_ankora_diff_diff_case", "label": "_diff_case()", "file_type": "code", "source_file": "src/ankora/diff.py", "source_location": "L95", "_callable": true}, {"id": "caseresult", "label": "CaseResult", "file_type": "code", "source_file": "", "source_location": "", "origin_file": "/Users/yajan/Desktop/evalgate/src/ankora/diff.py"}, {"id": "users_yajan_desktop_evalgate_src_ankora_diff_removed_case", "label": "_removed_case()", "file_type": "code", "source_file": "src/ankora/diff.py", "source_location": "L143", "_callable": true}, {"id": "users_yajan_desktop_evalgate_src_ankora_diff_aggregate_score", "label": "_aggregate_score()", "file_type": "code", "source_file": "src/ankora/diff.py", "source_location": "L154", "_callable": true}, {"id": "users_yajan_desktop_evalgate_src_ankora_diff_rationale_1", "label": "Compare a current RunResult against a baseline to classify per-case changes.  Th", "file_type": "rationale", "source_file": "src/ankora/diff.py", "source_location": "L1"}, {"id": "users_yajan_desktop_evalgate_src_ankora_diff_rationale_26", "label": "How a single case changed between baseline and current.", "file_type": "rationale", "source_file": "src/ankora/diff.py", "source_location": "L26"}, {"id": "users_yajan_desktop_evalgate_src_ankora_diff_rationale_37", "label": "The per-case comparison result.", "file_type": "rationale", "source_file": "src/ankora/diff.py", "source_location": "L37"}, {"id": "users_yajan_desktop_evalgate_src_ankora_diff_rationale_51", "label": "The full comparison plus roll-up counts and the gate signal.", "file_type": "rationale", "source_file": "src/ankora/diff.py", "source_location": "L51"}, {"id": "users_yajan_desktop_evalgate_src_ankora_diff_rationale_66", "label": "Compare ``current`` to ``baseline`` under ``config.gate.fail_on``.", "file_type": "rationale", "source_file": "src/ankora/diff.py", "source_location": "L66"}, {"id": "users_yajan_desktop_evalgate_src_ankora_diff_rationale_155", "label": "Mean of the case's scorer scores; falls back to pass/fail as 1.0/0.0.", "file_type": "rationale", "source_file": "src/ankora/diff.py", "source_location": "L155"}], "edges": [{"source": "users_yajan_desktop_evalgate_src_ankora_diff_py", "target": "collections", "relation": "imports_from", "context": "import", "confidence": "EXTRACTED", "source_file": "src/ankora/diff.py", "source_location": "L16", "weight": 1.0}, {"source": "users_yajan_desktop_evalgate_src_ankora_diff_py", "target": "enum", "relation": "imports_from", "context": "import", "confidence": "EXTRACTED", "source_file": "src/ankora/diff.py", "source_location": "L17", "weight": 1.0}, {"source": "users_yajan_desktop_evalgate_src_ankora_diff_py", "target": "pydantic", "relation": "imports_from", "context": "import", "confidence": "EXTRACTED", "source_file": "src/ankora/diff.py", "source_location": "L19", "weight": 1.0}, {"source": "users_yajan_desktop_evalgate_src_ankora_diff_py", "target": "ankora_config", "relation": "imports_from", "context": "import", "confidence": "EXTRACTED", "source_file": "src/ankora/diff.py", "source_location": "L21", "weight": 1.0}, {"source": "users_yajan_desktop_evalgate_src_ankora_diff_py", "target": "ankora_models", "relation": "imports_from", "context": "import", "confidence": "EXTRACTED", "source_file": "src/ankora/diff.py", "source_location": "L22", "weight": 1.0}, {"source": "users_yajan_desktop_evalgate_src_ankora_diff_py", "target": "users_yajan_desktop_evalgate_src_ankora_diff_casestatus", "relation": "contains", "confidence": "EXTRACTED", "source_file": "src/ankora/diff.py", "source_location": "L25", "weight": 1.0}, {"source": "users_yajan_desktop_evalgate_src_ankora_diff_casestatus", "target": "strenum", "relation": "inherits", "confidence": "EXTRACTED", "source_file": "src/ankora/diff.py", "source_location": "L25", "weight": 1.0}, {"source": "users_yajan_desktop_evalgate_src_ankora_diff_py", "target": "users_yajan_desktop_evalgate_src_ankora_diff_casediff", "relation": "contains", "confidence": "EXTRACTED", "source_file": "src/ankora/diff.py", "source_location": "L36", "weight": 1.0}, {"source": "users_yajan_desktop_evalgate_src_ankora_diff_casediff", "target": "basemodel", "relation": "inherits", "confidence": "EXTRACTED", "source_file": "src/ankora/diff.py", "source_location": "L36", "weight": 1.0}, {"source": "users_yajan_desktop_evalgate_src_ankora_diff_py", "target": "users_yajan_desktop_evalgate_src_ankora_diff_diffreport", "relation": "contains", "confidence": "EXTRACTED", "source_file": "src/ankora/diff.py", "source_location": "L50", "weight": 1.0}, {"source": "users_yajan_desktop_evalgate_src_ankora_diff_diffreport", "target": "basemodel", "relation": "inherits", "confidence": "EXTRACTED", "source_file": "src/ankora/diff.py", "source_location": "L50", "weight": 1.0}, {"source": "users_yajan_desktop_evalgate_src_ankora_diff_py", "target": "users_yajan_desktop_evalgate_src_ankora_diff_diff_runs", "relation": "contains", "confidence": "EXTRACTED", "source_file": "src/ankora/diff.py", "source_location": "L65", "weight": 1.0}, {"source": "users_yajan_desktop_evalgate_src_ankora_diff_diff_runs", "target": "runresult", "relation": "references", "context": "parameter_type", "confidence": "EXTRACTED", "source_file": "src/ankora/diff.py", "source_location": "L65", "weight": 1.0}, {"source": "users_yajan_desktop_evalgate_src_ankora_diff_diff_runs", "target": "runresult", "relation": "references", "context": "parameter_type", "confidence": "EXTRACTED", "source_file": "src/ankora/diff.py", "source_location": "L65", "weight": 1.0}, {"source": "users_yajan_desktop_evalgate_src_ankora_diff_diff_runs", "target": "config", "relation": "references", "context": "parameter_type", "confidence": "EXTRACTED", "source_file": "src/ankora/diff.py", "source_location": "L65", "weight": 1.0}, {"source": "users_yajan_desktop_evalgate_src_ankora_diff_diff_runs", "target": "users_yajan_desktop_evalgate_src_ankora_diff_diffreport", "relation": "references", "context": "return_type", "confidence": "EXTRACTED", "source_file": "src/ankora/diff.py", "source_location": "L65", "weight": 1.0}, {"source": "users_yajan_desktop_evalgate_src_ankora_diff_py", "target": "users_yajan_desktop_evalgate_src_ankora_diff_diff_case", "relation": "contains", "confidence": "EXTRACTED", "source_file": "src/ankora/diff.py", "source_location": "L95", "weight": 1.0}, {"source": "users_yajan_desktop_evalgate_src_ankora_diff_diff_case", "target": "caseresult", "relation": "references", "context": "parameter_type", "confidence": "EXTRACTED", "source_file": "src/ankora/diff.py", "source_location": "L95", "weight": 1.0}, {"source": "users_yajan_desktop_evalgate_src_ankora_diff_diff_case", "target": "caseresult", "relation": "references", "context": "parameter_type", "confidence": "EXTRACTED", "source_file": "src/ankora/diff.py", "source_location": "L95", "weight": 1.0}, {"source": "users_yajan_desktop_evalgate_src_ankora_diff_diff_case", "target": "users_yajan_desktop_evalgate_src_ankora_diff_casediff", "relation": "references", "context": "return_type", "confidence": "EXTRACTED", "source_file": "src/ankora/diff.py", "source_location": "L95", "weight": 1.0}, {"source": "users_yajan_desktop_evalgate_src_ankora_diff_py", "target": "users_yajan_desktop_evalgate_src_ankora_diff_removed_case", "relation": "contains", "confidence": "EXTRACTED", "source_file": "src/ankora/diff.py", "source_location": "L143", "weight": 1.0}, {"source": "users_yajan_desktop_evalgate_src_ankora_diff_removed_case", "target": "caseresult", "relation": "references", "context": "parameter_type", "confidence": "EXTRACTED", "source_file": "src/ankora/diff.py", "source_location": "L143", "weight": 1.0}, {"source": "users_yajan_desktop_evalgate_src_ankora_diff_removed_case", "target": "users_yajan_desktop_evalgate_src_ankora_diff_casediff", "relation": "references", "context": "return_type", "confidence": "EXTRACTED", "source_file": "src/ankora/diff.py", "source_location": "L143", "weight": 1.0}, {"source": "users_yajan_desktop_evalgate_src_ankora_diff_py", "target": "users_yajan_desktop_evalgate_src_ankora_diff_aggregate_score", "relation": "contains", "confidence": "EXTRACTED", "source_file": "src/ankora/diff.py", "source_location": "L154", "weight": 1.0}, {"source": "users_yajan_desktop_evalgate_src_ankora_diff_aggregate_score", "target": "caseresult", "relation": "references", "context": "parameter_type", "confidence": "EXTRACTED", "source_file": "src/ankora/diff.py", "source_location": "L154", "weight": 1.0}, {"source": "users_yajan_desktop_evalgate_src_ankora_diff_diff_runs", "target": "users_yajan_desktop_evalgate_src_ankora_diff_diff_case", "relation": "calls", "context": "call", "confidence": "EXTRACTED", "source_file": "src/ankora/diff.py", "source_location": "L74", "weight": 1.0}, {"source": "users_yajan_desktop_evalgate_src_ankora_diff_diff_runs", "target": "users_yajan_desktop_evalgate_src_ankora_diff_removed_case", "relation": "calls", "context": "call", "confidence": "EXTRACTED", "source_file": "src/ankora/diff.py", "source_location": "L78", "weight": 1.0}, {"source": "users_yajan_desktop_evalgate_src_ankora_diff_diff_runs", "target": "users_yajan_desktop_evalgate_src_ankora_diff_diffreport", "relation": "calls", "context": "call", "confidence": "EXTRACTED", "source_file": "src/ankora/diff.py", "source_location": "L81", "weight": 1.0}, {"source": "users_yajan_desktop_evalgate_src_ankora_diff_diff_case", "target": "users_yajan_desktop_evalgate_src_ankora_diff_aggregate_score", "relation": "calls", "context": "call", "confidence": "EXTRACTED", "source_file": "src/ankora/diff.py", "source_location": "L97", "weight": 1.0}, {"source": "users_yajan_desktop_evalgate_src_ankora_diff_diff_case", "target": "users_yajan_desktop_evalgate_src_ankora_diff_casediff", "relation": "calls", "context": "call", "confidence": "EXTRACTED", "source_file": "src/ankora/diff.py", "source_location": "L105", "weight": 1.0}, {"source": "users_yajan_desktop_evalgate_src_ankora_diff_removed_case", "target": "users_yajan_desktop_evalgate_src_ankora_diff_casediff", "relation": "calls", "context": "call", "confidence": "EXTRACTED", "source_file": "src/ankora/diff.py", "source_location": "L144", "weight": 1.0}, {"source": "users_yajan_desktop_evalgate_src_ankora_diff_removed_case", "target": "users_yajan_desktop_evalgate_src_ankora_diff_aggregate_score", "relation": "calls", "context": "call", "confidence": "EXTRACTED", "source_file": "src/ankora/diff.py", "source_location": "L148", "weight": 1.0}, {"source": "users_yajan_desktop_evalgate_src_ankora_diff_rationale_1", "target": "users_yajan_desktop_evalgate_src_ankora_diff_py", "relation": "rationale_for", "confidence": "EXTRACTED", "source_file": "src/ankora/diff.py", "source_location": "L1", "weight": 1.0}, {"source": "users_yajan_desktop_evalgate_src_ankora_diff_rationale_26", "target": "users_yajan_desktop_evalgate_src_ankora_diff_casestatus", "relation": "rationale_for", "confidence": "EXTRACTED", "source_file": "src/ankora/diff.py", "source_location": "L26", "weight": 1.0}, {"source": "users_yajan_desktop_evalgate_src_ankora_diff_rationale_37", "target": "users_yajan_desktop_evalgate_src_ankora_diff_casediff", "relation": "rationale_for", "confidence": "EXTRACTED", "source_file": "src/ankora/diff.py", "source_location": "L37", "weight": 1.0}, {"source": "users_yajan_desktop_evalgate_src_ankora_diff_rationale_51", "target": "users_yajan_desktop_evalgate_src_ankora_diff_diffreport", "relation": "rationale_for", "confidence": "EXTRACTED", "source_file": "src/ankora/diff.py", "source_location": "L51", "weight": 1.0}, {"source": "users_yajan_desktop_evalgate_src_ankora_diff_rationale_66", "target": "users_yajan_desktop_evalgate_src_ankora_diff_diff_runs", "relation": "rationale_for", "confidence": "EXTRACTED", "source_file": "src/ankora/diff.py", "source_location": "L66", "weight": 1.0}, {"source": "users_yajan_desktop_evalgate_src_ankora_diff_rationale_155", "target": "users_yajan_desktop_evalgate_src_ankora_diff_aggregate_score", "relation": "rationale_for", "confidence": "EXTRACTED", "source_file": "src/ankora/diff.py", "source_location": "L155", "weight": 1.0}], "raw_calls": [{"caller_nid": "users_yajan_desktop_evalgate_src_ankora_diff_diff_runs", "callee": "append", "is_member_call": true, "source_file": "/Users/yajan/Desktop/evalgate/src/ankora/diff.py", "source_location": "L74", "receiver": "cases"}, {"caller_nid": "users_yajan_desktop_evalgate_src_ankora_diff_diff_runs", "callee": "get", "is_member_call": true, "source_file": "/Users/yajan/Desktop/evalgate/src/ankora/diff.py", "source_location": "L74", "receiver": "baseline_by_id"}, {"caller_nid": "users_yajan_desktop_evalgate_src_ankora_diff_diff_runs", "callee": "append", "is_member_call": true, "source_file": "/Users/yajan/Desktop/evalgate/src/ankora/diff.py", "source_location": "L78", "receiver": "cases"}, {"caller_nid": "users_yajan_desktop_evalgate_src_ankora_diff_diff_runs", "callee": "Counter", "is_member_call": false, "source_file": "/Users/yajan/Desktop/evalgate/src/ankora/diff.py", "source_location": "L80", "receiver": null}]}